dapr/ext/fastapi/__init__.py
dapr/ext/fastapi/actor.py
dapr/ext/fastapi/app.py
dapr/ext/fastapi/version.py
dapr_ext_fastapi-1.16.0.dist-info/LICENSE
dapr_ext_fastapi-1.16.0.dist-info/METADATA
dapr_ext_fastapi-1.16.0.dist-info/WHEEL
dapr_ext_fastapi-1.16.0.dist-info/top_level.txt
dapr_ext_fastapi-1.16.0.dist-info/RECORD
